zibalPlatform/__init__.py
zibalPlatform/zibalPlatform.py
zibalPlatform-1.0.0.dist-info/LICENSE.txt
zibalPlatform-1.0.0.dist-info/METADATA
zibalPlatform-1.0.0.dist-info/WHEEL
zibalPlatform-1.0.0.dist-info/top_level.txt
zibalPlatform-1.0.0.dist-info/RECORD
