Metadata-Version: 2.1
Name: zibalPlatform
Version: 1.0.0
Summary: Zibal payment platform
Home-page: https://docs.zibal.ir/
Author: Yahya Kangi
Author-email: yhy.kng@gmail.com
License: MIT
Download-URL: https://pypi.org/project/zibalPlatform/
Keywords: Zibal,Payment,زیبال,درگاه پرداخت,درگاه زیبال,Platform,پلتفرم
Platform: UNKNOWN
Requires-Dist: requests
